gfESDdataMergeTools/__init__.py
gfESDdataMergeTools/main.py
gfESDdataMergeTools/app_logo/GFS.ico
gfESDdataMergeTools/scr/__init__.py
gfESDdataMergeTools/scr/hbmdatamerge.py
gfESDdataMergeTools/scr/mainwindow.py
gfESDdataMergeTools/scr/tlpdatamerge.py
gfESDdataMergeTools-1.0.0.dist-info/METADATA
gfESDdataMergeTools-1.0.0.dist-info/WHEEL
gfESDdataMergeTools-1.0.0.dist-info/entry_points.txt
gfESDdataMergeTools-1.0.0.dist-info/top_level.txt
gfESDdataMergeTools-1.0.0.dist-info/RECORD
